pyagxrobots/UGVConfigMsg.py
pyagxrobots/__init__.py
pyagxrobots/agxbase.py
pyagxrobots/agxrobots.py
pyagxrobots/pysdkugv.py
pyagxrobots/test.py
pyagxrobots-0.8.4.dist-info/LICENSE.txt
pyagxrobots-0.8.4.dist-info/METADATA
pyagxrobots-0.8.4.dist-info/WHEEL
pyagxrobots-0.8.4.dist-info/top_level.txt
pyagxrobots-0.8.4.dist-info/RECORD
