Metadata-Version: 2.1
Name: pyagxrobots
Version: 0.8.4
Summary: A small example package for agxrobots
Home-page: https://github.com/agilexrobotics/
Author: agilexrobotics
Author-email: support@agilex.ai
License: UNKNOWN
Project-URL: Bug Tracker, https://github.com/agilexrobotics/
Platform: UNKNOWN
Classifier: Programming Language :: Python :: 3.6
Classifier: Programming Language :: Python :: 3.7
Classifier: Programming Language :: Python :: 3.8
Classifier: Programming Language :: Python :: 3.9
Classifier: License :: OSI Approved :: MIT License
Requires-Python: >=3.6
License-File: LICENSE.txt
Requires-Dist: python-can (>=3.3.4)
